{"id": "osm-way-1530943551", "name": "วัดบ้านหลวง", "nameRoman": "", "aliases": ["วัดบ้านหลวง"], "type": "wat", "typeEn": "Buddhist temple (monastery)", "lat": 18.148463, "lng": 99.524891, "geoPrecision": "block", "province": "Lampang", "district": "", "subdistrict": "", "street": "", "heritage": "", "founded": "", "status": "active", "description": "", "phone": "", "email": "", "website": "", "openingHours": "", "confidence": "crawled", "sources": [{"type": "osm", "ref": "way/1530943551"}, {"type": "wikidata", "ref": "Q108865074"}, {"type": "wikipedia", "ref": "วัดบ้านหลวง (จังหวัดลำปาง)", "lang": "th", "url": "https://th.wikipedia.org/wiki/%E0%B8%A7%E0%B8%B1%E0%B8%94%E0%B8%9A%E0%B9%89%E0%B8%B2%E0%B8%99%E0%B8%AB%E0%B8%A5%E0%B8%A7%E0%B8%87_(%E0%B8%88%E0%B8%B1%E0%B8%87%E0%B8%AB%E0%B8%A7%E0%B8%B1%E0%B8%94%E0%B8%A5%E0%B8%B3%E0%B8%9B%E0%B8%B2%E0%B8%87)"}], "photoCount": 0, "photos": [], "provenance": {"summary": {"source": "wikipedia", "confidence": "crawled"}}, "summary": {"text": "วัดบ้านหลวง เป็นวัดราษฎร์สังกัดคณะสงฆ์ฝ่ายมหานิกาย ตั้งอยู่ในตำบลนาครัว อำเภอแม่ทะ จังหวัดลำปาง ที่ดินตั้งวัดมีเนื้อที่ 6 ไร่ 2 งาน 70 ตารางวา มีที่ธรณีสงฆ์จำนวน 1 แปลง เนื้อที่ 4 ไร่ 33 ตารางวา\nวัดบ้านหลวงสร้างเมื่อ พ.ศ. 2400 ได้รับพระราชทานวิสุงคามสีมาเมื่อวันที่ 5 เมษายน พ.ศ. 2517 เขตวิสุงคามสีมา กว้าง 10 เมตร ยาว 21 เมตร สถานที่ตั้งเดิมเป็นวัดเก่า ชื่อ วัดผาแป้น ซึ่งอยู่ทางทิศเหนือ ใกล้ทางเข้าสะพานบ้านเหนือหรือขัวสูง บริเวณป้อมยามตำรวจบ้านในปัจจุบัน ยังคงมีซากก้อนอิฐเก่าทับถมอยู่บนพื้น เชื่อว่ามีแผ่นหินผาอยู่ในบริเวณนั้น สันนิษฐานว่าวัดบ้านหลวง สร้างขึ้นราว พ.ศ. 2000 โดยพิจารณาจากพุทธลักษณะของพระเจ้าตองติ๊บ เป็นศิลปะเชียงแสน สิงห์ 2 หรือ สิงห์ 3 เนื่องจากมีฐานบัว และเจาะช่องไว้ที่ฐานพระ…", "title": "วัดบ้านหลวง (จังหวัดลำปาง)", "url": "https://th.wikipedia.org/wiki/%E0%B8%A7%E0%B8%B1%E0%B8%94%E0%B8%9A%E0%B9%89%E0%B8%B2%E0%B8%99%E0%B8%AB%E0%B8%A5%E0%B8%A7%E0%B8%87_(%E0%B8%88%E0%B8%B1%E0%B8%87%E0%B8%AB%E0%B8%A7%E0%B8%B1%E0%B8%94%E0%B8%A5%E0%B8%B3%E0%B8%9B%E0%B8%B2%E0%B8%87)", "lang": "th", "license": "CC BY-SA 4.0", "licenseUrl": "https://creativecommons.org/licenses/by-sa/4.0/"}, "article": {"th": {"lang": "th", "title": "วัดบ้านหลวง (จังหวัดลำปาง)", "url": "https://th.wikipedia.org/wiki/%E0%B8%A7%E0%B8%B1%E0%B8%94%E0%B8%9A%E0%B9%89%E0%B8%B2%E0%B8%99%E0%B8%AB%E0%B8%A5%E0%B8%A7%E0%B8%87_(%E0%B8%88%E0%B8%B1%E0%B8%87%E0%B8%AB%E0%B8%A7%E0%B8%B1%E0%B8%94%E0%B8%A5%E0%B8%B3%E0%B8%9B%E0%B8%B2%E0%B8%87)", "license": "CC BY-SA 4.0", "licenseUrl": "https://creativecommons.org/licenses/by-sa/4.0/", "text": "วัดบ้านหลวง เป็นวัดราษฎร์สังกัดคณะสงฆ์ฝ่ายมหานิกาย ตั้งอยู่ในตำบลนาครัว อำเภอแม่ทะ จังหวัดลำปาง ที่ดินตั้งวัดมีเนื้อที่ 6 ไร่ 2 งาน 70 ตารางวา มีที่ธรณีสงฆ์จำนวน 1 แปลง เนื้อที่ 4 ไร่ 33 ตารางวา\nวัดบ้านหลวงสร้างเมื่อ พ.ศ. 2400 ได้รับพระราชทานวิสุงคามสีมาเมื่อวันที่ 5 เมษายน พ.ศ. 2517 เขตวิสุงคามสีมา กว้าง 10 เมตร ยาว 21 เมตร สถานที่ตั้งเดิมเป็นวัดเก่า ชื่อ วัดผาแป้น ซึ่งอยู่ทางทิศเหนือ ใกล้ทางเข้าสะพานบ้านเหนือหรือขัวสูง บริเวณป้อมยามตำรวจบ้านในปัจจุบัน ยังคงมีซากก้อนอิฐเก่าทับถมอยู่บนพื้น เชื่อว่ามีแผ่นหินผาอยู่ในบริเวณนั้น สันนิษฐานว่าวัดบ้านหลวง สร้างขึ้นราว พ.ศ. 2000 โดยพิจารณาจากพุทธลักษณะของพระเจ้าตองติ๊บ เป็นศิลปะเชียงแสน สิงห์ 2 หรือ สิงห์ 3 เนื่องจากมีฐานบัว และเจาะช่องไว้ที่ฐานพระ…", "sections": [{"heading": "รายนามเจ้าอาวาส", "kind": null, "text": "พระครูจันทร์คำ สงเคราะห์ พ.ศ. 2501–2503\nพระสุแก้ว สิริธมฺโม พ.ศ. 2503–2505\nพระอธิการธำรง ธมฺมกาโม พ.ศ. 2505–\nพระครูสังวรณ์ ฐานวโร"}], "chars": 1440}}, "kind": "wat", "facets": {"kind": ["wat"], "province": ["Lampang"], "hasPhotograph": [false], "articleLanguages": ["th"], "confidence": ["crawled"]}, "url": "https://wichaa.net/place/osm-way-1530943551/", "threads": [{"rel": "near", "label": "วัดเหมี้ยง", "note": "589 m", "href": "/place/osm-way-1530943549/"}, {"rel": "near", "label": "วัดบ้านจว้าก", "note": "1064 m", "href": "/place/wat-chawak/"}]}