{"manuscript": {"id": 1637, "key": "DLNTM (CrossAsia)::1640", "title": "Pali mahāpaṭṭhāna pakaraṇa mat pai", "titleThai": "บาฬีมหาปัฏฐานปกอรณ์ มัดปาย", "titleTranslit": "Pali mahāpaṭṭhāna pakaraṇa mat pai", "source": "DLNTM (CrossAsia)", "sourceIdentifier": "1640", "tradition": "Lanna manuscripts", "genre": "buddhist_canonical", "genreLabel": "Buddhist Canonical · พระไตรปิฎก", "genreRaw": "Abhidhamma", "priority": 0, "script": "tham_lanna", "scriptLabel": "Tham Lanna · อักษรธรรมล้านนา", "scriptFamily": "Tham (Dhamma)", "language": "Monolingual Pali", "languages": ["Pali"], "subgenre": "Abhidhamma", "material": "palm_leaf", "materialLabel": "Palm-leaf · ใบลาน", "materialFamily": "Palm-leaf", "province": "Phrae", "provenance": "Wat Sung Men", "geoLevel": "temple", "temple": "Sung Men District", "date": "1196 (Cunlasakkalat (CS))", "era": "CS", "century": "19th", "extentPages": 81, "imageCount": 1, "pageCount": 0, "subjects": [], "dateCe": 1834, "sourceUrl": "https://iiif.crossasia.org/s/lanna/collections/554808/manifests/556445", "iiifManifestUrl": "https://iiif.crossasia.org/s/lanna/madoc/api/manifests/556445/export/source", "firstSeen": "2026-07-08T12:37:38.229092+00:00", "lastSeen": "2026-07-08T12:37:38.229092+00:00", "rawMetadata": {"id": 556445, "thumbnail": "https://iiif-content.crossasia.org/xasia/dlntm+1640+1640_106719/full/512,/0/default.jpg", "published": true, "source": "https://itr02.crossasia.org/fcrepo/rest/dlntm/1640/manifest", "viewingDirection": "left-to-right", "metadata": [{"label": {"en": ["title"]}, "value": {"en": ["Pali mahāpaṭṭhāna pakaraṇa mat pai"], "th": ["บาฬีมหาปัฏฐานปกอรณ์ มัดปาย"]}}, {"label": {"en": ["dc:language"]}, "value": {"en": ["Monolingual Pali"], "th": ["บาลีล้วน"]}}, {"label": {"none": ["dc:identifier"]}, "value": {"none": ["1640"]}}, {"label": {"none": ["otherIdentifier.code_number"]}, "value": {"none": ["070104242_00"]}}, {"value": {"en": ["Wat Sung Men", "Phrae", "Sung Men District"], "th": ["จ. แพร่", "อ. สูงเม่น", "วัดสูงเม่น"]}, "label": {"en": ["dc:place"]}}, {"label": {"en": ["full_location_name"]}, "value": {"en": ["Wat Sung Men, Phrae, Sung Men District"], "th": ["วัดสูงเม่น, จ. แพร่, อ. สูงเม่น"]}}, {"label": {"en": ["lanna_original"]}, "value": {"none": ["documents_id : 1640", "otherIdentifier.code_number : 070104242_00", "otherIdentifier.roll : 185", "documents_number_of_fascicles : 14", "documents_number_of_folios : 262", "full_location_name : Wat Sung Men, Sung Men District, Phrae", "full_location_name_lao : วัดสูงเม่น, อ. สูงเม่น, จ. แพร่", "documents_has_colophon : yes", "documents_is_illustrated : no", "documents_is_color : no", "locations_id : 107", "documents_is_complete : yes", "documents_pages_count : 81", "materials_name : [\"Palm-leaf\"]", "materials_name_lao : [\"ใบลาน\"]", "locations_gps_lat : [18.053288]", "locations_gps_lon : [100.113459]", "ancillary_terms_roman : [\"bali / pālī\"]", "exact_coordinates : true", "year : 1196", "locations_dlntm_loc_code : 107", "ancillary_terms_lao : [\"บาลี\"]", "public_remarks_english : Date is 'pi kap sa-nga.'", "public_remarks_lao : ปีจารเป็นปีกาบสง้า", "categories_name : [\"Abhidhamma\"]", "categories_name_lao : [\"พระอภิธรรม\"]", "languages : [\"Monolingual Pali\"]", "languages_lao : [\"บาลีล้วน\"]", "scripts : [\"Tham Lan Na\"]", "scripts_lao : [\"ธรรมล้านนา\"]", "title_search_roman : [\"mahapatthan / mahāpaṭṭhāna\"]", "title_search_lao : [\"มหาปัฏฐาน\"]", "dllm_title_roman : [\"Pali mahāpaṭṭhāna pakaraṇa mat pai\"]", "dllm_title_lao : [\"บาฬีมหาปัฏฐานปกอรณ์ มัดปาย\"]", "plmp_title_lao : [\"บาลีมหาปัฏฐานปกอร / มหาปัฏฐานปกอรณ์\"]", "legibilities_name : Mostly legible", "legibilities_name_lao : ส่วนมากอ่านได้", "conditions_name : Slightly damaged", "conditions_name_lao : ชำรุดบ้าง", "documents_preferred_date_system : Cunlasakkalat (CS)", "documents_preferred_date_system_lao : จุลศักราช (จ.ศ.)", "documents_date_written : 1834", "in_collection : Preservation of Northern Thai Manuscripts Project (PNTMP)"]}}, {"label": {"en": ["dc:description"]}, "value": {"en": ["Microfilm roll no.:185", "Date is 'pi kap sa-nga.'"], "th": ["ปีจารเป็นปีกาบสง้า"]}}, {"label": {"none": ["has_colophon"]}, "value": {"none": ["yes"]}}, {"label": {"none": ["is_illustrated"]}, "value": {"none": ["no"]}}, {"label": {"none": ["is_color"]}, "value": {"none": ["no"]}}, {"label": {"none": ["is_complete"]}, "value": {"none": ["yes"]}}, {"label": {"none": ["in_collection"]}, "value": {"none": ["Preservation of Northern Thai Manuscripts Project (PNTMP)"]}}, {"label": {"none": ["pages_count"]}, "value": {"none": ["81"]}}, {"label": {"en": ["material"]}, "value": {"en": ["Palm-leaf"], "th": ["ใบลาน"]}}, {"label": {"none": ["schema:latitude"]}, "value": {"none": ["18.053288"]}}, {"label": {"none": ["schema:longitude"]}, "value": {"none": ["100.113459"]}}, {"label": {"en": ["schema:keywords"]}, "value": {"en": ["bali / pālī"], "th": ["บาลี"]}}, {"label": {"en": ["dc:subject"]}, "value": {"en": ["Abhidhamma"], "th": ["พระอภิธรรม"]}}, {"label": {"en": ["script"]}, "value": {"en": ["Tham Lan Na"], "th": ["ธรรมล้านนา"]}}, {"label": {"en": ["index"]}, "value": {"th": ["มหาปัฏฐาน", "บาลีมหาปัฏฐานปกอร / มหาปัฏฐานปกอรณ์"], "en": ["mahapatthan / mahāpaṭṭhāna"]}}, {"label": {"en": ["legibilities"]}, "value": {"en": ["Mostly legible"], "th": ["ส่วนมากอ่านได้"]}}, {"label": {"en": ["conditions"]}, "value": {"en": ["Slightly damaged"], "th": ["ชำรุดบ้าง"]}}, {"value": {"none": ["185"]}, "label": {"none": ["otherIdentifier.roll"]}}, {"label": {"en": ["dc:extent"]}, "value": {"none": ["14 fascicle(s), 262 folio(s) (81 img.)"]}}, {"label": {"none": ["exact_coordinates"]}, "value": {"none": ["true"]}}, {"label": {"none": ["dc:date"]}, "value": {"none": ["1834"]}}, {"label": {"en": ["date_original"]}, "value": {"en": ["1196 (Cunlasakkalat (CS))"], "th": ["1196 (จุลศักราช (จ.ศ.))"]}}, {"label": {"none": ["map"]}, "value": {"none": ["<a href=\"#\" onClick=\"MyWindow=window.open('https://www.openstreetmap.org/?mlat=18.053288&mlon=100.113459#map=16/18.053288/100.113459','Map','width=500,height=500'); return false;\">Map view</a>"]}}], "label": {"none": ["Pali mahāpaṭṭhāna pakaraṇa mat pai (บาฬีมหาปัฏฐานปกอรณ์ มัดปาย)"]}, "summary": {"none": ["Digital Library of Northern Thai Manuscripts  -  Code:070104242_00 (lanna_1640)"]}, "requiredStatement": {"label": {"en": ["Attribution"]}, "value": {"en": ["Images and metadata are made available by the Chiang Mai University Library in cooperation with the National Library of Laos (CC BY-NC 4.0) via the Staatsbibliothek zu Berlin | CrossAsia"]}}, "items": [{"id": 650352, "thumbnail": "https://iiif-content.crossasia.org/xasia/dlntm+1640+1640_106717/full/512,/0/default.jpg", "published": true, "label": {"none": ["[ 1 ]"]}}, {"id": 650350, "thumbnail": "https://iiif-content.crossasia.org/xasia/dlntm+1640+1640_106719/full/512,/0/default.jpg", "published": true, "label": {"none": ["[ 2 ]"]}}, {"id": 650355, "thumbnail": "https://iiif-content.crossasia.org/xasia/dlntm+1640+1640_106721/full/512,/0/default.jpg", "published": true, "label": {"none": ["[ 3 ]"]}}, {"id": 650351, "thumbnail": "https://iiif-content.crossasia.org/xasia/dlntm+1640+1640_106723/full/512,/0/default.jpg", "published": true, "label": {"none": ["[ 4 ]"]}}, {"id": 650353, "thumbnail": "https://iiif-content.crossasia.org/xasia/dlntm+1640+1640_106725/full/512,/0/default.jpg", "published": true, "label": {"none": ["[ 5 ]"]}}, {"id": 650356, "thumbnail": "https://iiif-content.crossasia.org/xasia/dlntm+1640+1640_106727/full/512,/0/default.jpg", "published": true, "label": {"none": ["[ 6 ]"]}}, {"id": 650354, "thumbnail": "https://iiif-content.crossasia.org/xasia/dlntm+1640+1640_106729/full/512,/0/default.jpg", "published": true, "label": {"none": ["[ 7 ]"]}}, {"id": 650357, "thumbnail": "https://iiif-content.crossasia.org/xasia/dlntm+1640+1640_106731/full/512,/0/default.jpg", "published": true, "label": {"none": ["[ 8 ]"]}}, {"id": 650360, "thumbnail": "https://iiif-content.crossasia.org/xasia/dlntm+1640+1640_106733/full/512,/0/default.jpg", "published": true, "label": {"none": ["[ 9 ]"]}}, {"id": 650361, "thumbnail": "https://iiif-content.crossasia.org/xasia/dlntm+1640+1640_106735/full/512,/0/default.jpg", "published": true, "label": {"none": ["[ 10 ]"]}}, {"id": 650359, "thumbnail": "https://iiif-content.crossasia.org/xasia/dlntm+1640+1640_106737/full/512,/0/default.jpg", "published": true, "label": {"none": ["[ 11 ]"]}}, {"id": 650358, "thumbnail": "https://iiif-content.crossasia.org/xasia/dlntm+1640+1640_106739/full/512,/0/default.jpg", "published": true, "label": {"none": ["[ 12 ]"]}}, {"id": 650365, "thumbnail": "https://iiif-content.crossasia.org/xasia/dlntm+1640+1640_106741/full/512,/0/default.jpg", "published": true, "label": {"none": ["[ 13 ]"]}}, {"id": 650370, "thumbnail": "https://iiif-content.crossasia.org/xasia/dlntm+1640+1640_106743/full/512,/0/default.jpg", "published": true, "label": {"none": ["[ 14 ]"]}}, {"id": 650362, "thumbnail": "https://iiif-content.crossasia.org/xasia/dlntm+1640+1640_106718/full/512,/0/default.jpg", "published": true, "label": {"none": ["[ 15 ]"]}}, {"id": 650364, "thumbnail": "https://iiif-content.crossasia.org/xasia/dlntm+1640+1640_106716/full/512,/0/default.jpg", "published": true, "label": {"none": ["[ 16 ]"]}}, {"id": 650363, "thumbnail": "https://iiif-content.crossasia.org/xasia/dlntm+1640+1640_106720/full/512,/0/default.jpg", "published": true, "label": {"none": ["[ 17 ]"]}}, {"id": 650367, "thumbnail": "https://iiif-content.crossasia.org/xasia/dlntm+1640+1640_106722/full/512,/0/default.jpg", "published": true, "label": {"none": ["[ 18 ]"]}}, {"id": 650368, "thumbnail": "https://iiif-content.crossasia.org/xasia/dlntm+1640+1640_106724/full/512,/0/default.jpg", "published": true, "label": {"none": ["[ 19 ]"]}}, {"id": 650366, "thumbnail": "https://iiif-content.crossasia.org/xasia/dlntm+1640+1640_106726/full/512,/0/default.jpg", "published": true, "label": {"none": ["[ 20 ]"]}}, {"id": 650369, "thumbnail": "https://iiif-content.crossasia.org/xasia/dlntm+1640+1640_106728/full/512,/0/default.jpg", "published": true, "label": {"none": ["[ 21 ]"]}}, {"id": 650371, "thumbnail": "https://iiif-content.crossasia.org/xasia/dlntm+1640+1640_106730/full/512,/0/default.jpg", "published": true, "label": {"none": ["[ 22 ]"]}}, {"id": 650376, "thumbnail": "https://iiif-content.crossasia.org/xasia/dlntm+1640+1640_106732/full/512,/0/default.jpg", "published": true, "label": {"none": ["[ 23 ]"]}}, {"id": 650372, "thumbnail": "https://iiif-content.crossasia.org/xasia/dlntm+1640+1640_106734/full/512,/0/default.jpg", "published": true, "label": {"none": ["[ 24 ]"]}}, {"id": 650374, "thumbnail": "https://iiif-content.crossasia.org/xasia/dlntm+1640+1640_106736/full/512,/0/default.jpg", "published": true, "label": {"none": ["[ 25 ]"]}}, {"id": 650373, "thumbnail": "https://iiif-content.crossasia.org/xasia/dlntm+1640+1640_106738/full/512,/0/default.jpg", "published": true, "label": {"none": ["[ 26 ]"]}}, {"id": 650375, "thumbnail": "https://iiif-content.crossasia.org/xasia/dlntm+1640+1640_106740/full/512,/0/default.jpg", "published": true, "label": {"none": ["[ 27 ]"]}}, {"id": 650377, "thumbnail": "https://iiif-content.crossasia.org/xasia/dlntm+1640+1640_106745/full/512,/0/default.jpg", "published": true, "label": {"none": ["[ 28 ]"]}}]}, "images": [{"sequence": 0, "sha256": "71d97f3a5184bd23300ab83ff233c0f90d0dd17fbf944d061c7ab2f8220a59ae", "status": "downloaded", "bytes": 71922, "sourceUrl": "https://iiif-content.crossasia.org/xasia/dlntm+1640+1640_106717/full/512,/0/default.jpg", "hasLocal": false, "ocr": "", "ocrEngine": "", "ocrScript": "", "ocrConf": null}], "iiifThumb": "", "pages": [], "diagramPages": 0, "related": [{"facet": "temple", "value": "Sung Men District", "label": "Sung Men District", "items": [{"id": 2269, "title": "Anuloka sasana"}, {"id": 2412, "title": "Mahawibak hom"}, {"id": 2225, "title": "Mathulatsa wahini"}, {"id": 1691, "title": "Nisai ha sip sat mat hok"}, {"id": 2288, "title": "Nisai nantha pakon"}, {"id": 1222, "title": "Pali angkhuttala nikai panca nibat"}]}, {"facet": "genre", "value": "buddhist_canonical", "label": "Buddhist Canonical · พระไตรปิฎก", "items": [{"id": 1867, "title": "Abbhāna suddanta"}, {"id": 1873, "title": "Abbhāna suddanta parivāsa"}, {"id": 1869, "title": "Abbhāna suddanta parivāso"}, {"id": 6954, "title": "Abhidhamma Kankae"}, {"id": 1139, "title": "Akalawatta sut"}, {"id": 1950, "title": "Akkhala namo"}]}, {"facet": "province", "value": "Wat Sung Men", "label": "Wat Sung Men", "items": [{"id": 2269, "title": "Anuloka sasana"}, {"id": 2412, "title": "Mahawibak hom"}, {"id": 2225, "title": "Mathulatsa wahini"}, {"id": 1691, "title": "Nisai ha sip sat mat hok"}, {"id": 2288, "title": "Nisai nantha pakon"}, {"id": 1222, "title": "Pali angkhuttala nikai panca nibat"}]}], "hasReader": false, "threads": [{"rel": "held_at", "href": "/browse?temple=Sung%20Men%20District", "label": "Sung Men District", "note": ""}]}, "annotation": {"notes": "", "tags": []}}