{"manuscript": {"id": 2321, "key": "DLNTM (CrossAsia)::2324", "title": "Thisotattaki", "titleThai": "ธิโสทัตตกี", "titleTranslit": "Thisotattaki", "source": "DLNTM (CrossAsia)", "sourceIdentifier": "2324", "genre": "jataka", "genreLabel": "Jātaka · ชาดก", "genreRaw": "Jataka", "priority": 0, "script": "tham_lanna", "scriptLabel": "Tham Lanna · อักษรธรรมล้านนา", "scriptFamily": "Tham (Dhamma)", "language": "Pali and Lan Na", "languages": ["Pali", "Lan Na"], "subgenre": "Jataka", "material": "palm_leaf", "materialLabel": "Palm-leaf · ใบลาน", "province": "Phrae", "provenance": "Phrae", "geoLevel": "province", "temple": "Wat Sung Men", "date": "1200 (Cunlasakkalat (CS))", "century": "19th", "extentPages": 9, "imageCount": 0, "dateCe": 1838, "sourceUrl": "https://iiif.crossasia.org/s/lanna/collections/554808/manifests/557129", "iiifManifestUrl": "https://iiif.crossasia.org/s/lanna/madoc/api/manifests/557129/export/source", "firstSeen": "2026-07-08T13:23:34.202566+00:00", "lastSeen": "2026-07-08T13:23:34.202566+00:00", "rawMetadata": {"id": 557129, "thumbnail": "https://iiif-content.crossasia.org/xasia/dlntm+2324+2324_132134/full/512,/0/default.jpg", "published": true, "source": "https://itr02.crossasia.org/fcrepo/rest/dlntm/2324/manifest", "viewingDirection": "left-to-right", "label": {"none": ["Thisotattaki (ธิโสทัตตกี)"]}, "summary": {"none": ["Digital Library of Northern Thai Manuscripts  -  Code:070120077_08 (lanna_2324)"]}, "metadata": [{"label": {"en": ["title"]}, "value": {"en": ["Thisotattaki"], "th": ["ธิโสทัตตกี"]}}, {"label": {"en": ["dc:language"]}, "value": {"en": ["Pali and Lan Na"], "th": ["บาลี และ ล้านนา"]}}, {"label": {"none": ["dc:identifier"]}, "value": {"none": ["2324"]}}, {"label": {"none": ["otherIdentifier.code_number"]}, "value": {"none": ["070120077_08"]}}, {"label": {"en": ["dc:place"]}, "value": {"en": ["Phrae", "Sung Men District", "Wat Sung Men"], "th": ["จ. แพร่", "อ. สูงเม่น", "วัดสูงเม่น"]}}, {"label": {"en": ["full_location_name"]}, "value": {"en": ["Wat Sung Men, Phrae, Sung Men District"], "th": ["วัดสูงเม่น, จ. แพร่, อ. สูงเม่น"]}}, {"label": {"en": ["lanna_original"]}, "value": {"none": ["documents_id : 2324", "otherIdentifier.code_number : 070120077_08", "otherIdentifier.roll : 231", "documents_number_of_fascicles : 1", "documents_number_of_folios : 27", "full_location_name : Wat Sung Men, Sung Men District, Phrae", "full_location_name_lao : วัดสูงเม่น, อ. สูงเม่น, จ. แพร่", "documents_has_colophon : no", "documents_is_illustrated : no", "documents_is_color : no", "locations_id : 107", "documents_is_complete : yes", "documents_pages_count : 9", "materials_name : [\"Palm-leaf\"]", "materials_name_lao : [\"ใบลาน\"]", "locations_gps_lat : [18.053288]", "locations_gps_lon : [100.113459]", "exact_coordinates : true", "year : 1200", "locations_dlntm_loc_code : 107", "public_remarks_english : Date is 'pi poek set.'", "public_remarks_lao : ปีจารเป็นปีเปิกเส็ด", "categories_name : [\"Jataka\"]", "categories_name_lao : [\"ชาดก\"]", "languages : [\"Pali and Lan Na\"]", "languages_lao : [\"บาลี และ ล้านนา\"]", "scripts : [\"Tham Lan Na\"]", "scripts_lao : [\"ธรรมล้านนา\"]", "title_search_roman : [\"sothantaki / sothattaki\"]", "title_search_lao : [\"โสทันตกี / โสทัตตกี \"]", "dllm_title_roman : [\"Thisotattaki\"]", "dllm_title_lao : [\"ธิโสทัตตกี\"]", "plmp_title_lao : [\"โสทันตกี\"]", "legibilities_name : Mostly legible", "legibilities_name_lao : ส่วนมากอ่านได้", "conditions_name : Slightly damaged", "conditions_name_lao : ชำรุดบ้าง", "documents_preferred_date_system : Cunlasakkalat (CS)", "documents_preferred_date_system_lao : จุลศักราช (จ.ศ.)", "documents_date_written : 1838", "in_collection : Preservation of Northern Thai Manuscripts Project (PNTMP)"]}}, {"label": {"en": ["dc:description"]}, "value": {"en": ["Microfilm roll no.:231", "Date is 'pi poek set.'"], "th": ["ปีจารเป็นปีเปิกเส็ด"]}}, {"label": {"none": ["has_colophon"]}, "value": {"none": ["no"]}}, {"label": {"none": ["is_illustrated"]}, "value": {"none": ["no"]}}, {"label": {"none": ["is_color"]}, "value": {"none": ["no"]}}, {"label": {"none": ["is_complete"]}, "value": {"none": ["yes"]}}, {"label": {"none": ["in_collection"]}, "value": {"none": ["Preservation of Northern Thai Manuscripts Project (PNTMP)"]}}, {"label": {"none": ["pages_count"]}, "value": {"none": ["9"]}}, {"label": {"en": ["material"]}, "value": {"en": ["Palm-leaf"], "th": ["ใบลาน"]}}, {"label": {"none": ["schema:latitude"]}, "value": {"none": ["18.053288"]}}, {"label": {"none": ["schema:longitude"]}, "value": {"none": ["100.113459"]}}, {"label": {"en": ["dc:subject"]}, "value": {"en": ["Jataka"], "th": ["ชาดก"]}}, {"label": {"en": ["script"]}, "value": {"en": ["Tham Lan Na"], "th": ["ธรรมล้านนา"]}}, {"label": {"en": ["index"]}, "value": {"th": ["โสทันตกี / โสทัตตกี ", "โสทันตกี"], "en": ["sothantaki / sothattaki"]}}, {"label": {"en": ["legibilities"]}, "value": {"en": ["Mostly legible"], "th": ["ส่วนมากอ่านได้"]}}, {"label": {"en": ["conditions"]}, "value": {"en": ["Slightly damaged"], "th": ["ชำรุดบ้าง"]}}, {"label": {"none": ["otherIdentifier.roll"]}, "value": {"none": ["231"]}}, {"label": {"en": ["dc:extent"]}, "value": {"none": ["1 fascicle(s), 27 folio(s) (9 img.)"]}}, {"label": {"none": ["exact_coordinates"]}, "value": {"none": ["true"]}}, {"label": {"none": ["dc:date"]}, "value": {"none": ["1838"]}}, {"label": {"en": ["date_original"]}, "value": {"en": ["1200 (Cunlasakkalat (CS))"], "th": ["1200 (จุลศักราช (จ.ศ.))"]}}, {"label": {"none": ["map"]}, "value": {"none": ["<a href=\"#\" onClick=\"MyWindow=window.open('https://www.openstreetmap.org/?mlat=18.053288&mlon=100.113459#map=16/18.053288/100.113459','Map','width=500,height=500'); return false;\">Map view</a>"]}}], "requiredStatement": {"label": {"en": ["Attribution"]}, "value": {"en": ["Images and metadata are made available by the Chiang Mai University Library in cooperation with the National Library of Laos (CC BY-NC 4.0) via the Staatsbibliothek zu Berlin | CrossAsia"]}}, "items": [{"id": 674819, "thumbnail": "https://iiif-content.crossasia.org/xasia/dlntm+2324+2324_132134/full/512,/0/default.jpg", "published": true, "label": {"none": ["[ 1 ]"]}}, {"id": 674823, "thumbnail": "https://iiif-content.crossasia.org/xasia/dlntm+2324+2324_132135/full/512,/0/default.jpg", "published": true, "label": {"none": ["[ 2 ]"]}}, {"id": 674821, "thumbnail": "https://iiif-content.crossasia.org/xasia/dlntm+2324+2324_132136/full/512,/0/default.jpg", "published": true, "label": {"none": ["[ 3 ]"]}}, {"id": 674824, "thumbnail": "https://iiif-content.crossasia.org/xasia/dlntm+2324+2324_132137/full/512,/0/default.jpg", "published": true, "label": {"none": ["[ 4 ]"]}}, {"id": 674826, "thumbnail": "https://iiif-content.crossasia.org/xasia/dlntm+2324+2324_132138/full/512,/0/default.jpg", "published": true, "label": {"none": ["[ 5 ]"]}}, {"id": 674827, "thumbnail": "https://iiif-content.crossasia.org/xasia/dlntm+2324+2324_132139/full/512,/0/default.jpg", "published": true, "label": {"none": ["[ 6 ]"]}}, {"id": 674830, "thumbnail": "https://iiif-content.crossasia.org/xasia/dlntm+2324+2324_132140/full/512,/0/default.jpg", "published": true, "label": {"none": ["[ 7 ]"]}}, {"id": 674828, "thumbnail": "https://iiif-content.crossasia.org/xasia/dlntm+2324+2324_132141/full/512,/0/default.jpg", "published": true, "label": {"none": ["[ 8 ]"]}}, {"id": 674831, "thumbnail": "https://iiif-content.crossasia.org/xasia/dlntm+2324+2324_132142/full/512,/0/default.jpg", "published": true, "label": {"none": ["[ 9 ]"]}}, {"id": 674825, "thumbnail": "https://iiif-content.crossasia.org/xasia/dlntm+2324+2324_132143/full/512,/0/default.jpg", "published": true, "label": {"none": ["[ 10 ]"]}}]}, "images": [], "iiifThumb": "https://iiif-content.crossasia.org/xasia/dlntm+2324+2324_132134/full/800,/0/default.jpg", "related": [{"facet": "temple", "value": "Wat Sung Men", "label": "Wat Sung Men", "items": [{"id": 1876, "title": "Boek lem"}, {"id": 1882, "title": "Catula kammatthan"}, {"id": 2426, "title": "Lam sut nangsue kan kae"}, {"id": 2193, "title": "Loek 27 tua"}, {"id": 2528, "title": "Lokathina sangkhep"}, {"id": 2604, "title": "Nangsue hiak khwan khwai"}]}, {"facet": "genre", "value": "jataka", "label": "Jātaka · ชาดก", "items": [{"id": 4325, "title": "Ai bun kwang"}, {"id": 3241, "title": "Ai hoi kap lan"}, {"id": 6396, "title": "Ai hoi kap lan"}, {"id": 3215, "title": "Ai loi khot"}, {"id": 4277, "title": "Ai loi khot"}, {"id": 4341, "title": "Akittila"}]}, {"facet": "province", "value": "Phrae", "label": "Phrae", "items": [{"id": 1876, "title": "Boek lem"}, {"id": 2646, "title": "Cantapahana withi sekkhalakanitasalampa"}, {"id": 2661, "title": "Cantawahana withi"}, {"id": 1882, "title": "Catula kammatthan"}, {"id": 2736, "title": "Khwan luang"}, {"id": 2426, "title": "Lam sut nangsue kan kae"}]}]}, "annotation": {"notes": "", "tags": []}}