{"manuscript": {"id": 36, "key": "DLNTM (CrossAsia)::36", "title": "Vohan katha phuk song", "titleThai": "โวหารกะถา ผูก ๒", "titleTranslit": "Vohan katha phuk song", "source": "DLNTM (CrossAsia)", "sourceIdentifier": "36", "genre": "buddhist_canonical", "genreLabel": "Buddhist Canonical · พระไตรปิฎก", "genreRaw": "Abhidhamma", "priority": 0, "script": "tham_lao", "scriptLabel": "Tham Lao · อักษรธรรมลาว", "language": "Pali and Lao", "material": "palm_leaf", "materialLabel": "Palm-leaf · ใบลาน", "province": "Chiang Mai", "temple": "Wat Phra Sing Woramahawihan", "date": "Undated", "century": "", "extentPages": 4, "imageCount": 1, "dateCe": null, "sourceUrl": "https://iiif.crossasia.org/s/lanna/collections/554808/manifests/554830", "iiifManifestUrl": "https://iiif.crossasia.org/s/lanna/madoc/api/manifests/554830/export/source", "firstSeen": "2026-07-08T10:48:28.500636+00:00", "lastSeen": "2026-07-08T10:48:28.500636+00:00", "rawMetadata": {"id": 554830, "thumbnail": "https://iiif-content.crossasia.org/xasia/dlntm+36+36_206922/full/512,/0/default.jpg", "published": true, "source": "https://itr02.crossasia.org/fcrepo/rest/dlntm/36/manifest", "viewingDirection": "left-to-right", "label": {"none": ["Vohan katha phuk song (โวหารกะถา ผูก ๒)"]}, "summary": {"none": ["Digital Library of Northern Thai Manuscripts  -  Code:010707032_00 (lanna_36)"]}, "metadata": [{"label": {"en": ["title"]}, "value": {"en": ["Vohan katha phuk song"], "th": ["โวหารกะถา ผูก ๒"]}}, {"label": {"en": ["dc:language"]}, "value": {"en": ["Pali and Lao"], "th": ["บาลี และ ลาว"]}}, {"label": {"none": ["dc:identifier"]}, "value": {"none": ["36"]}}, {"label": {"none": ["otherIdentifier.code_number"]}, "value": {"none": ["010707032_00"]}}, {"label": {"en": ["dc:place"]}, "value": {"en": ["Chiang Mai", "Mueang District", "Wat Phra Sing Woramahawihan"], "th": ["จ. เชียงใหม่", "อ. เมือง", "วัดพระสิงห์วรมหาวิหาร"]}}, {"label": {"en": ["full_location_name"]}, "value": {"en": ["Wat Phra Sing Woramahawihan, Chiang Mai, Mueang District"], "th": ["วัดพระสิงห์วรมหาวิหาร, จ. เชียงใหม่, อ. เมือง"]}}, {"label": {"en": ["lanna_original"]}, "value": {"none": ["documents_id : 36", "otherIdentifier.code_number : 010707032_00", "documents_number_of_fascicles : 1", "documents_number_of_folios : 12", "full_location_name : Wat Phra Sing Woramahawihan, Mueang District, Chiang Mai", "full_location_name_lao : วัดพระสิงห์วรมหาวิหาร, อ. เมือง, จ. เชียงใหม่", "documents_has_colophon : no", "documents_is_illustrated : no", "documents_is_color : yes", "locations_id : 7", "documents_is_complete : yes", "documents_pages_count : 4", "materials_name : [\"Palm-leaf\"]", "materials_name_lao : [\"ใบลาน\"]", "locations_gps_lat : [18.788535]", "locations_gps_lon : [98.981865]", "ancillary_terms_roman : [\"wohan / vohāra\"]", "exact_coordinates : true", "locations_dlntm_loc_code : 7", "ancillary_terms_lao : [\"โวหาร\"]", "categories_name : [\"Abhidhamma\"]", "categories_name_lao : [\"พระอภิธรรม\"]", "languages : [\"Pali and Lao\"]", "languages_lao : [\"บาลี และ ลาว\"]", "scripts : [\"Tham Lao\"]", "scripts_lao : [\"ธรรมลาว\"]", "title_search_roman : [\"wohan katha\"]", "title_search_lao : [\"โวหารกะถา\"]", "dllm_title_roman : [\"Vohan katha phuk song\"]", "dllm_title_lao : [\"โวหารกะถา ผูก ๒\"]", "plmp_title_lao : [\"โวหารกถา ผูก ๒\"]", "legibilities_name : Good legibility", "legibilities_name_lao : อ่านได้ดี", "conditions_name : Good", "conditions_name_lao : ดี", "documents_preferred_date_system : Undated", "documents_preferred_date_system_lao : ปีจารไม่ปรากฏ", "in_collection : Digital Library of Northern Thai Manuscripts (DLNTM)"]}}, {"label": {"none": ["has_colophon"]}, "value": {"none": ["no"]}}, {"label": {"none": ["is_illustrated"]}, "value": {"none": ["no"]}}, {"label": {"none": ["is_color"]}, "value": {"none": ["yes"]}}, {"label": {"none": ["is_complete"]}, "value": {"none": ["yes"]}}, {"label": {"none": ["in_collection"]}, "value": {"none": ["Digital Library of Northern Thai Manuscripts (DLNTM)"]}}, {"label": {"none": ["pages_count"]}, "value": {"none": ["4"]}}, {"label": {"en": ["material"]}, "value": {"en": ["Palm-leaf"], "th": ["ใบลาน"]}}, {"label": {"none": ["schema:latitude"]}, "value": {"none": ["18.788535"]}}, {"label": {"none": ["schema:longitude"]}, "value": {"none": ["98.981865"]}}, {"label": {"en": ["schema:keywords"]}, "value": {"en": ["wohan / vohāra"], "th": ["โวหาร"]}}, {"label": {"en": ["dc:subject"]}, "value": {"en": ["Abhidhamma"], "th": ["พระอภิธรรม"]}}, {"label": {"en": ["script"]}, "value": {"en": ["Tham Lao"], "th": ["ธรรมลาว"]}}, {"label": {"en": ["index"]}, "value": {"th": ["โวหารกะถา", "โวหารกถา ผูก ๒"], "en": ["wohan katha"]}}, {"label": {"en": ["legibilities"]}, "value": {"en": ["Good legibility"], "th": ["อ่านได้ดี"]}}, {"label": {"en": ["conditions"]}, "value": {"en": ["Good"], "th": ["ดี"]}}, {"label": {"en": ["dc:extent"]}, "value": {"none": ["1 fascicle(s), 12 folio(s) (4 img.)"]}}, {"label": {"none": ["exact_coordinates"]}, "value": {"none": ["true"]}}, {"label": {"en": ["date_original"]}, "value": {"en": ["Undated"], "th": ["ปีจารไม่ปรากฏ"]}}, {"label": {"none": ["map"]}, "value": {"none": ["<a href=\"#\" onClick=\"MyWindow=window.open('https://www.openstreetmap.org/?mlat=18.788535&mlon=98.981865#map=16/18.788535/98.981865','Map','width=500,height=500'); return false;\">Map view</a>"]}}], "requiredStatement": {"label": {"en": ["Attribution"]}, "value": {"en": ["Images and metadata are made available by the National Library of Laos (CC BY-NC 4.0) via the Staatsbibliothek zu Berlin | CrossAsia"]}}, "items": [{"id": 561817, "thumbnail": "https://iiif-content.crossasia.org/xasia/dlntm+36+36_206922/full/512,/0/default.jpg", "published": true, "label": {"none": ["[ 1 ]"]}}, {"id": 561820, "thumbnail": "https://iiif-content.crossasia.org/xasia/dlntm+36+36_206920/full/512,/0/default.jpg", "published": true, "label": {"none": ["[ 2 ]"]}}, {"id": 561822, "thumbnail": "https://iiif-content.crossasia.org/xasia/dlntm+36+36_206921/full/512,/0/default.jpg", "published": true, "label": {"none": ["[ 3 ]"]}}, {"id": 561824, "thumbnail": "https://iiif-content.crossasia.org/xasia/dlntm+36+36_206923/full/512,/0/default.jpg", "published": true, "label": {"none": ["[ 4 ]"]}}]}, "images": [{"sequence": 0, "sha256": "59e8e1e23ddbe1179ae9972daecf712793737a4aee14cf968067933f9c7487a1", "status": "downloaded", "bytes": 31502, "sourceUrl": "https://iiif-content.crossasia.org/xasia/dlntm+36+36_206922/full/512,/0/default.jpg", "hasLocal": false, "ocr": "", "ocrEngine": "", "ocrScript": "", "ocrConf": null}], "related": [{"facet": "temple", "value": "Wat Phra Sing Woramahawihan", "label": "Wat Phra Sing Woramahawihan", "items": [{"id": 48, "title": "Kham wai that"}, {"id": 47, "title": "Ongkalakkhana an hue tan lae haksa sin metta phawana"}, {"id": 45, "title": "Ton sabap khian nangsue ongkalakkhana kong tan pha mahakathin"}, {"id": 43, "title": "Uppatet suep cata"}, {"id": 27, "title": "Anisong"}, {"id": 25, "title": "Anisong pha bangsakun"}]}, {"facet": "genre", "value": "buddhist_canonical", "label": "Buddhist Canonical · พระไตรปิฎก", "items": [{"id": 1867, "title": "Abbhāna suddanta"}, {"id": 1873, "title": "Abbhāna suddanta parivāsa"}, {"id": 1869, "title": "Abbhāna suddanta parivāso"}, {"id": 6954, "title": "Abhidhamma Kankae"}, {"id": 1139, "title": "Akalawatta sut"}, {"id": 1950, "title": "Akkhala namo"}]}, {"facet": "province", "value": "Chiang Mai", "label": "Chiang Mai", "items": [{"id": 4470, "title": "Athimat winitsai"}, {"id": 3723, "title": "Buddhābhiseka gāthā"}, {"id": 6067, "title": "Cumnum itipiso, Pha holaman"}, {"id": 6084, "title": "Inthanin singkaha, Sut nyom simma"}, {"id": 765, "title": "Kam wai pha cao tang muan lae wai that hom tang muan"}, {"id": 813, "title": "Ken sutthatin"}]}]}, "annotation": {"notes": "", "tags": []}}