{"manuscript": {"id": 57, "key": "DLNTM (CrossAsia)::57", "title": "Tua sonthi", "titleThai": "ตัวสนธิ", "titleTranslit": "Tua sonthi", "source": "DLNTM (CrossAsia)", "sourceIdentifier": "57", "genre": "grammar_lexicography", "genreLabel": "Grammar & Lexicography · ไวยากรณ์", "genreRaw": "Philology", "priority": 0, "script": "tham_lanna", "scriptLabel": "Tham Lanna · อักษรธรรมล้านนา", "scriptFamily": "Tham (Dhamma)", "language": "Pali and Lan Na", "languages": ["Pali", "Lan Na"], "subgenre": "Philology", "material": "palm_leaf", "materialLabel": "Palm-leaf · ใบลาน", "materialFamily": "Palm-leaf", "province": "Chiang Mai", "provenance": "Chiang Mai", "geoLevel": "province", "temple": "Wat Phra Sing Woramahawihan", "date": "1201 (Cunlasakkalat (CS))", "era": "CS", "century": "19th", "extentPages": 6, "imageCount": 1, "pageCount": 0, "subjects": [], "dateCe": 1839, "sourceUrl": "https://iiif.crossasia.org/s/lanna/collections/554808/manifests/554865", "iiifManifestUrl": "https://iiif.crossasia.org/s/lanna/madoc/api/manifests/554865/export/source", "firstSeen": "2026-07-08T10:49:20.832242+00:00", "lastSeen": "2026-07-08T10:49:20.832242+00:00", "rawMetadata": {"id": 554865, "thumbnail": "https://iiif-content.crossasia.org/xasia/dlntm+57+57_207239/full/512,/0/default.jpg", "published": true, "source": "https://itr02.crossasia.org/fcrepo/rest/dlntm/57/manifest", "viewingDirection": "left-to-right", "label": {"none": ["Tua sonthi (ตัวสนธิ)"]}, "summary": {"none": ["Digital Library of Northern Thai Manuscripts  -  Code:010716996_00 (lanna_57)"]}, "metadata": [{"label": {"en": ["title"]}, "value": {"en": ["Tua sonthi"], "th": ["ตัวสนธิ"]}}, {"label": {"en": ["dc:language"]}, "value": {"en": ["Pali and Lan Na"], "th": ["บาลี และ ล้านนา"]}}, {"label": {"none": ["dc:identifier"]}, "value": {"none": ["57"]}}, {"label": {"none": ["otherIdentifier.code_number"]}, "value": {"none": ["010716996_00"]}}, {"label": {"en": ["dc:place"]}, "value": {"en": ["Chiang Mai", "Mueang District", "Wat Phra Sing Woramahawihan"], "th": ["จ. เชียงใหม่", "อ. เมือง", "วัดพระสิงห์วรมหาวิหาร"]}}, {"label": {"en": ["full_location_name"]}, "value": {"en": ["Wat Phra Sing Woramahawihan, Chiang Mai, Mueang District"], "th": ["วัดพระสิงห์วรมหาวิหาร, จ. เชียงใหม่, อ. เมือง"]}}, {"label": {"en": ["lanna_original"]}, "value": {"none": ["documents_id : 57", "otherIdentifier.code_number : 010716996_00", "documents_number_of_fascicles : 2", "documents_number_of_folios : 14", "full_location_name : Wat Phra Sing Woramahawihan, Mueang District, Chiang Mai", "full_location_name_lao : วัดพระสิงห์วรมหาวิหาร, อ. เมือง, จ. เชียงใหม่", "documents_has_colophon : yes", "documents_is_illustrated : no", "documents_is_color : yes", "locations_id : 7", "documents_is_complete : no", "documents_pages_count : 6", "materials_name : [\"Palm-leaf\"]", "materials_name_lao : [\"ใบลาน\"]", "locations_gps_lat : [18.788535]", "locations_gps_lon : [98.981865]", "exact_coordinates : true", "year : 1201", "locations_dlntm_loc_code : 7", "public_remarks_lao : ปีจารเป็นปีกัดไค้", "categories_name : [\"Philology\"]", "categories_name_lao : [\"ตำราอักษรศาสตร์\"]", "languages : [\"Pali and Lan Na\"]", "languages_lao : [\"บาลี และ ล้านนา\"]", "scripts : [\"Tham Lan Na\"]", "scripts_lao : [\"ธรรมล้านนา\"]", "title_search_roman : [\"sonthi / sandhi\"]", "title_search_lao : [\"สนธิ\"]", "dllm_title_roman : [\"Tua sonthi\"]", "dllm_title_lao : [\"ตัวสนธิ\"]", "plmp_title_lao : [\"สนฺธิกปฺเปทสสุตฺตสงฺคโห ปณฺจโม กณฺโท\"]", "legibilities_name : Good legibility", "legibilities_name_lao : อ่านได้ดี", "conditions_name : Good", "conditions_name_lao : ดี", "documents_preferred_date_system : Cunlasakkalat (CS)", "documents_preferred_date_system_lao : จุลศักราช (จ.ศ.)", "documents_date_written : 1839", "in_collection : Digital Library of Northern Thai Manuscripts (DLNTM)"]}}, {"label": {"en": ["dc:description"]}, "value": {"th": ["ปีจารเป็นปีกัดไค้"]}}, {"label": {"none": ["has_colophon"]}, "value": {"none": ["yes"]}}, {"label": {"none": ["is_illustrated"]}, "value": {"none": ["no"]}}, {"label": {"none": ["is_color"]}, "value": {"none": ["yes"]}}, {"label": {"none": ["is_complete"]}, "value": {"none": ["no"]}}, {"label": {"none": ["in_collection"]}, "value": {"none": ["Digital Library of Northern Thai Manuscripts (DLNTM)"]}}, {"label": {"none": ["pages_count"]}, "value": {"none": ["6"]}}, {"label": {"en": ["material"]}, "value": {"en": ["Palm-leaf"], "th": ["ใบลาน"]}}, {"label": {"none": ["schema:latitude"]}, "value": {"none": ["18.788535"]}}, {"label": {"none": ["schema:longitude"]}, "value": {"none": ["98.981865"]}}, {"label": {"en": ["dc:subject"]}, "value": {"en": ["Philology"], "th": ["ตำราอักษรศาสตร์"]}}, {"label": {"en": ["script"]}, "value": {"en": ["Tham Lan Na"], "th": ["ธรรมล้านนา"]}}, {"label": {"en": ["index"]}, "value": {"th": ["สนธิ", "สนฺธิกปฺเปทสสุตฺตสงฺคโห ปณฺจโม กณฺโท"], "en": ["sonthi / sandhi"]}}, {"label": {"en": ["legibilities"]}, "value": {"en": ["Good legibility"], "th": ["อ่านได้ดี"]}}, {"label": {"en": ["conditions"]}, "value": {"en": ["Good"], "th": ["ดี"]}}, {"label": {"en": ["dc:extent"]}, "value": {"none": ["2 fascicle(s), 14 folio(s) (6 img.)"]}}, {"label": {"none": ["exact_coordinates"]}, "value": {"none": ["true"]}}, {"label": {"none": ["dc:date"]}, "value": {"none": ["1839"]}}, {"label": {"en": ["date_original"]}, "value": {"en": ["1201 (Cunlasakkalat (CS))"], "th": ["1201 (จุลศักราช (จ.ศ.))"]}}, {"label": {"none": ["map"]}, "value": {"none": ["<a href=\"#\" onClick=\"MyWindow=window.open('https://www.openstreetmap.org/?mlat=18.788535&mlon=98.981865#map=16/18.788535/98.981865','Map','width=500,height=500'); return false;\">Map view</a>"]}}], "requiredStatement": {"label": {"en": ["Attribution"]}, "value": {"en": ["Images and metadata are made available by the National Library of Laos (CC BY-NC 4.0) via the Staatsbibliothek zu Berlin | CrossAsia"]}}, "items": [{"id": 562847, "thumbnail": "https://iiif-content.crossasia.org/xasia/dlntm+57+57_207242/full/512,/0/default.jpg", "published": true, "label": {"none": ["[ 1 ]"]}}, {"id": 562848, "thumbnail": "https://iiif-content.crossasia.org/xasia/dlntm+57+57_207240/full/512,/0/default.jpg", "published": true, "label": {"none": ["[ 2 ]"]}}, {"id": 562846, "thumbnail": "https://iiif-content.crossasia.org/xasia/dlntm+57+57_207239/full/512,/0/default.jpg", "published": true, "label": {"none": ["[ 3 ]"]}}, {"id": 562850, "thumbnail": "https://iiif-content.crossasia.org/xasia/dlntm+57+57_207241/full/512,/0/default.jpg", "published": true, "label": {"none": ["[ 4 ]"]}}, {"id": 562849, "thumbnail": "https://iiif-content.crossasia.org/xasia/dlntm+57+57_207237/full/512,/0/default.jpg", "published": true, "label": {"none": ["[ 5 ]"]}}, {"id": 562854, "thumbnail": "https://iiif-content.crossasia.org/xasia/dlntm+57+57_207238/full/512,/0/default.jpg", "published": true, "label": {"none": ["[ 6 ]"]}}]}, "images": [{"sequence": 0, "sha256": "6baabc381e677172a3100cb638c2c1b1c18a1ca339a8495a49cf957ce54b211b", "status": "downloaded", "bytes": 30601, "sourceUrl": "https://iiif-content.crossasia.org/xasia/dlntm+57+57_207242/full/512,/0/default.jpg", "hasLocal": false, "ocr": "", "ocrEngine": "", "ocrScript": "", "ocrConf": null}], "iiifThumb": "", "pages": [], "diagramPages": 0, "related": [{"facet": "temple", "value": "Wat Phra Sing Woramahawihan", "label": "Wat Phra Sing Woramahawihan", "items": [{"id": 48, "title": "Kham wai that"}, {"id": 47, "title": "Ongkalakkhana an hue tan lae haksa sin metta phawana"}, {"id": 45, "title": "Ton sabap khian nangsue ongkalakkhana kong tan pha mahakathin"}, {"id": 43, "title": "Uppatet suep cata"}, {"id": 27, "title": "Anisong"}, {"id": 25, "title": "Anisong pha bangsakun"}]}, {"facet": "genre", "value": "grammar_lexicography", "label": "Grammar & Lexicography · ไวยากรณ์", "items": [{"id": 295, "title": "Akhanyat"}, {"id": 2040, "title": "Akhanyat"}, {"id": 2501, "title": "Akhanyat"}, {"id": 3802, "title": "Akhanyat"}, {"id": 4722, "title": "Akhanyat"}, {"id": 6249, "title": "Akhanyat"}]}, {"facet": "province", "value": "Chiang Mai", "label": "Chiang Mai", "items": [{"id": 4470, "title": "Athimat winitsai"}, {"id": 3723, "title": "Buddhābhiseka gāthā"}, {"id": 6067, "title": "Cumnum itipiso, Pha holaman"}, {"id": 6084, "title": "Inthanin singkaha, Sut nyom simma"}, {"id": 765, "title": "Kam wai pha cao tang muan lae wai that hom tang muan"}, {"id": 813, "title": "Ken sutthatin"}]}], "hasReader": false}, "annotation": {"notes": "", "tags": []}}