{"dbPresent": true, "dbPath": "catalog.db", "storeDir": "store", "counts": {"manuscripts": 6990, "priority": 665, "images": 20152, "imagesDownloaded": 20152, "imagesPending": 0}, "sources": [{"name": "British Library — Digital Library of Thai Manuscripts", "base_url": "https://www.bl.uk/manuscripts", "api_type": "unknown", "status": "not_crawled", "last_crawled": null}, {"name": "CMU Digital Heritage Collection (Chiang Mai University)", "base_url": "https://cmudc.library.cmu.ac.th", "api_type": "unknown", "status": "not_crawled", "last_crawled": null}, {"name": "Cleveland Museum of Art (Open Access)", "base_url": "https://www.clevelandart.org", "api_type": "rest_json", "status": "crawled", "last_crawled": "2026-07-18T13:31:31.880678+00:00"}, {"name": "Contributed Thai texts (Downloads haul 2026-07-09)", "base_url": "local:contributed/thai_wichaa_texts", "api_type": "contributed", "status": "crawled", "last_crawled": null}, {"name": "DLNTM (CrossAsia)", "base_url": "https://lannamanuscripts.net", "api_type": "madoc_api", "status": "crawled", "last_crawled": "2026-07-18T13:30:45.759056+00:00"}, {"name": "DLNTM — Digital Library of Northern Thai Manuscripts", "base_url": "https://lannamanuscripts.net", "api_type": "unknown", "status": "not_crawled", "last_crawled": null}, {"name": "Digital Library of Lao Manuscripts", "base_url": "https://laomanuscripts.net", "api_type": "unknown", "status": "not_crawled", "last_crawled": null}, {"name": "EFEO Lanna Manuscripts", "base_url": "https://lanna-manuscripts.efeo.fr", "api_type": "html", "status": "crawled", "last_crawled": "2026-07-18T13:30:46.656045+00:00"}, {"name": "EFEO Lanna Manuscripts (คัมภีร์ล้านนา)", "base_url": "https://lanna-manuscripts.efeo.fr", "api_type": "unknown", "status": "not_crawled", "last_crawled": null}, {"name": "Endangered Archives Programme (EAP) — Thai/Tai manuscripts", "base_url": "https://eap.bl.uk", "api_type": "unknown", "status": "not_crawled", "last_crawled": null}, {"name": "Lazada Singapore (amulet commerce)", "base_url": "https://www.lazada.sg", "api_type": "playwright_dom", "status": "crawled", "last_crawled": "2026-07-18T12:49:39.589052+00:00"}, {"name": "Lazada Thailand (amulet commerce)", "base_url": "https://www.lazada.co.th", "api_type": "playwright_dom", "status": "crawled", "last_crawled": "2026-07-18T13:30:51.342929+00:00"}, {"name": "LearnMore textbooks (contributed)", "base_url": "https://drive.google.com/file/d/1QBWpnlpzfHLHHHzmF1K371lH-ZR0264z/view", "api_type": "contributed", "status": "crawled", "last_crawled": null}, {"name": "NIU SEA Digital Library (Northern Illinois University)", "base_url": "https://sea.lib.niu.edu", "api_type": "unknown", "status": "not_crawled", "last_crawled": null}, {"name": "Preservation of Northern Thai Manuscripts Project (PNTMP)", "base_url": "http://www.thaimanuscripts.de", "api_type": "unknown", "status": "not_crawled", "last_crawled": null}, {"name": "SAC — Princess Maha Chakri Sirindhorn Anthropology Centre (Bangkok)", "base_url": "https://www.sac.or.th", "api_type": "unknown", "status": "not_crawled", "last_crawled": null}, {"name": "Smithsonian Open Access", "base_url": "https://www.si.edu", "api_type": "rest_json", "status": "crawled", "last_crawled": "2026-07-18T13:32:31.516730+00:00"}, {"name": "Southeast Asian Library Group (SEALG)", "base_url": "https://southeastasianlibrarygroup.wordpress.com", "api_type": "unknown", "status": "not_crawled", "last_crawled": null}, {"name": "The Metropolitan Museum of Art (Open Access)", "base_url": "https://www.metmuseum.org", "api_type": "rest_json", "status": "crawled", "last_crawled": "2026-07-18T13:32:01.872857+00:00"}, {"name": "[tm.de] Digital Heritage Collections, Chiang Mai University", "base_url": "http://library.cmu.ac.th/digital_collection/digitalheritage/", "api_type": "unknown", "status": "discovered", "last_crawled": null}, {"name": "[tm.de] Digital Library of Lao Manuscripts, National Library of Laos", "base_url": "http://www.laomanuscripts.net/en/index", "api_type": "unknown", "status": "discovered", "last_crawled": null}, {"name": "[tm.de] Digital Library of Northern Thai Manuscripts", "base_url": "http://lannamanuscripts.net/en", "api_type": "unknown", "status": "discovered", "last_crawled": null}, {"name": "[tm.de] Digital Library of Thai Manuscripts, British Library London", "base_url": "http://britishlibrary.typepad.co.uk/asian-and-african/thai.html", "api_type": "unknown", "status": "discovered", "last_crawled": null}, {"name": "[tm.de] Manuscripts of Western Thailand", "base_url": "http://www.sac.or.th/databases/manuscripts/main.php?m=document&p=index", "api_type": "unknown", "status": "discovered", "last_crawled": null}, {"name": "[tm.de] Senmai, Shan Buddhist manuscripts in the UK", "base_url": "https://senmai.bodleian.ox.ac.uk/", "api_type": "unknown", "status": "discovered", "last_crawled": null}, {"name": "[tm.de] Tai Ahom Manuscripts of Assam", "base_url": "https://eap.bl.uk/project/EAP373", "api_type": "unknown", "status": "discovered", "last_crawled": null}, {"name": "[tm.de] Thai manuscsripts, Chester Beatty Library, Dublin", "base_url": "https://viewer.cbl.ie/viewer/search/-/-/1/RANDOM/DC%3Athaicollection/", "api_type": "unknown", "status": "discovered", "last_crawled": null}], "log": [{"ts": "2026-07-18T13:32:31.515971+00:00", "source": "Smithsonian Open Access", "action": "api_page", "ref": "Indonesia#start16900", "http_status": null, "n_records": 0, "status": "done", "notes": ""}, {"ts": "2026-07-18T13:32:29.020012+00:00", "source": "Smithsonian Open Access", "action": "api_page", "ref": "Java#start16900", "http_status": null, "n_records": 0, "status": "done", "notes": ""}, {"ts": "2026-07-18T13:32:26.464291+00:00", "source": "Smithsonian Open Access", "action": "api_page", "ref": "Champa#start16900", "http_status": null, "n_records": 0, "status": "done", "notes": ""}, {"ts": "2026-07-18T13:32:23.975750+00:00", "source": "Smithsonian Open Access", "action": "api_page", "ref": "Vietnam#start16900", "http_status": null, "n_records": 0, "status": "done", "notes": ""}, {"ts": "2026-07-18T13:32:21.636286+00:00", "source": "Smithsonian Open Access", "action": "api_page", "ref": "Burmese#start16900", "http_status": null, "n_records": 0, "status": "done", "notes": ""}, {"ts": "2026-07-18T13:32:19.113456+00:00", "source": "Smithsonian Open Access", "action": "api_page", "ref": "Burma#start16900", "http_status": null, "n_records": 0, "status": "done", "notes": ""}, {"ts": "2026-07-18T13:32:16.616128+00:00", "source": "Smithsonian Open Access", "action": "api_page", "ref": "Cambodia#start16900", "http_status": null, "n_records": 0, "status": "done", "notes": ""}, {"ts": "2026-07-18T13:32:14.124853+00:00", "source": "Smithsonian Open Access", "action": "api_page", "ref": "Khmer#start16900", "http_status": null, "n_records": 0, "status": "done", "notes": ""}, {"ts": "2026-07-18T13:32:11.609658+00:00", "source": "Smithsonian Open Access", "action": "api_page", "ref": "Lao#start17000", "http_status": null, "n_records": 0, "status": "done", "notes": ""}, {"ts": "2026-07-18T13:32:09.263195+00:00", "source": "Smithsonian Open Access", "action": "api_page", "ref": "Lanna#start17000", "http_status": null, "n_records": 0, "status": "done", "notes": ""}, {"ts": "2026-07-18T13:32:06.768297+00:00", "source": "Smithsonian Open Access", "action": "api_page", "ref": "Thai#start17000", "http_status": null, "n_records": 0, "status": "done", "notes": ""}, {"ts": "2026-07-18T13:32:04.264849+00:00", "source": "Smithsonian Open Access", "action": "api_page", "ref": "Thailand#start17100", "http_status": null, "n_records": 0, "status": "done", "notes": ""}, {"ts": "2026-07-18T13:32:01.868767+00:00", "source": "The Metropolitan Museum of Art (Open Access)", "action": "object", "ref": "39179", "http_status": null, "n_records": 0, "status": "error", "notes": "Client error '404 Not Found' for url 'https://collectionapi.metmuseum.org/public/collection/v1/objects/39179'\nFor more information check: https://developer.mozilla.org/en-US/docs/Web/HTTP/Status/404"}, {"ts": "2026-07-18T13:31:59.984679+00:00", "source": "The Metropolitan Museum of Art (Open Access)", "action": "object", "ref": "38315", "http_status": null, "n_records": 0, "status": "error", "notes": "Client error '404 Not Found' for url 'https://collectionapi.metmuseum.org/public/collection/v1/objects/38315'\nFor more information check: https://developer.mozilla.org/en-US/docs/Web/HTTP/Status/404"}, {"ts": "2026-07-18T13:31:58.164618+00:00", "source": "The Metropolitan Museum of Art (Open Access)", "action": "object", "ref": "825638", "http_status": null, "n_records": 0, "status": "error", "notes": "Client error '404 Not Found' for url 'https://collectionapi.metmuseum.org/public/collection/v1/objects/825638'\nFor more information check: https://developer.mozilla.org/en-US/docs/Web/HTTP/Status/404"}, {"ts": "2026-07-18T13:31:56.340920+00:00", "source": "The Metropolitan Museum of Art (Open Access)", "action": "object", "ref": "39097", "http_status": null, "n_records": 0, "status": "error", "notes": "Client error '404 Not Found' for url 'https://collectionapi.metmuseum.org/public/collection/v1/objects/39097'\nFor more information check: https://developer.mozilla.org/en-US/docs/Web/HTTP/Status/404"}, {"ts": "2026-07-18T13:31:54.396388+00:00", "source": "The Metropolitan Museum of Art (Open Access)", "action": "object", "ref": "38315", "http_status": null, "n_records": 0, "status": "error", "notes": "Client error '404 Not Found' for url 'https://collectionapi.metmuseum.org/public/collection/v1/objects/38315'\nFor more information check: https://developer.mozilla.org/en-US/docs/Web/HTTP/Status/404"}, {"ts": "2026-07-18T13:31:52.511285+00:00", "source": "The Metropolitan Museum of Art (Open Access)", "action": "object", "ref": "73158", "http_status": null, "n_records": 0, "status": "error", "notes": "Expecting value: line 1 column 1 (char 0)"}, {"ts": "2026-07-18T13:31:52.509487+00:00", "source": "The Metropolitan Museum of Art (Open Access)", "action": "object", "ref": "39184", "http_status": null, "n_records": 0, "status": "error", "notes": "Client error '404 Not Found' for url 'https://collectionapi.metmuseum.org/public/collection/v1/objects/39184'\nFor more information check: https://developer.mozilla.org/en-US/docs/Web/HTTP/Status/404"}, {"ts": "2026-07-18T13:31:50.686043+00:00", "source": "The Metropolitan Museum of Art (Open Access)", "action": "object", "ref": "38301", "http_status": null, "n_records": 0, "status": "error", "notes": "Client error '404 Not Found' for url 'https://collectionapi.metmuseum.org/public/collection/v1/objects/38301'\nFor more information check: https://developer.mozilla.org/en-US/docs/Web/HTTP/Status/404"}, {"ts": "2026-07-18T13:31:48.850292+00:00", "source": "The Metropolitan Museum of Art (Open Access)", "action": "object", "ref": "39198", "http_status": null, "n_records": 0, "status": "error", "notes": "Expecting value: line 1 column 1 (char 0)"}, {"ts": "2026-07-18T13:31:48.848748+00:00", "source": "The Metropolitan Museum of Art (Open Access)", "action": "object", "ref": "38296", "http_status": null, "n_records": 0, "status": "error", "notes": "Expecting value: line 1 column 1 (char 0)"}, {"ts": "2026-07-18T13:31:48.848436+00:00", "source": "The Metropolitan Museum of Art (Open Access)", "action": "object", "ref": "51302", "http_status": null, "n_records": 0, "status": "error", "notes": "Expecting value: line 1 column 1 (char 0)"}, {"ts": "2026-07-18T13:31:48.847960+00:00", "source": "The Metropolitan Museum of Art (Open Access)", "action": "object", "ref": "39996", "http_status": null, "n_records": 0, "status": "error", "notes": "Expecting value: line 1 column 1 (char 0)"}, {"ts": "2026-07-18T13:31:48.847448+00:00", "source": "The Metropolitan Museum of Art (Open Access)", "action": "object", "ref": "50668", "http_status": null, "n_records": 0, "status": "error", "notes": "Expecting value: line 1 column 1 (char 0)"}, {"ts": "2026-07-18T13:31:48.846947+00:00", "source": "The Metropolitan Museum of Art (Open Access)", "action": "object", "ref": "72341", "http_status": null, "n_records": 0, "status": "error", "notes": "Expecting value: line 1 column 1 (char 0)"}, {"ts": "2026-07-18T13:31:48.846469+00:00", "source": "The Metropolitan Museum of Art (Open Access)", "action": "object", "ref": "72387", "http_status": null, "n_records": 0, "status": "error", "notes": "Expecting value: line 1 column 1 (char 0)"}, {"ts": "2026-07-18T13:31:48.846089+00:00", "source": "The Metropolitan Museum of Art (Open Access)", "action": "object", "ref": "39994", "http_status": null, "n_records": 0, "status": "error", "notes": "Expecting value: line 1 column 1 (char 0)"}, {"ts": "2026-07-18T13:31:48.845556+00:00", "source": "The Metropolitan Museum of Art (Open Access)", "action": "object", "ref": "39769", "http_status": null, "n_records": 0, "status": "error", "notes": "Expecting value: line 1 column 1 (char 0)"}, {"ts": "2026-07-18T13:31:48.845050+00:00", "source": "The Metropolitan Museum of Art (Open Access)", "action": "object", "ref": "39606", "http_status": null, "n_records": 0, "status": "error", "notes": "Expecting value: line 1 column 1 (char 0)"}, {"ts": "2026-07-18T13:31:48.844611+00:00", "source": "The Metropolitan Museum of Art (Open Access)", "action": "object", "ref": "53955", "http_status": null, "n_records": 0, "status": "error", "notes": "Expecting value: line 1 column 1 (char 0)"}, {"ts": "2026-07-18T13:31:48.843847+00:00", "source": "The Metropolitan Museum of Art (Open Access)", "action": "object", "ref": "38447", "http_status": null, "n_records": 0, "status": "error", "notes": "Expecting value: line 1 column 1 (char 0)"}, {"ts": "2026-07-18T13:31:48.842772+00:00", "source": "The Metropolitan Museum of Art (Open Access)", "action": "object", "ref": "38300", "http_status": null, "n_records": 0, "status": "error", "notes": "Expecting value: line 1 column 1 (char 0)"}, {"ts": "2026-07-18T13:31:48.842140+00:00", "source": "The Metropolitan Museum of Art (Open Access)", "action": "object", "ref": "904942", "http_status": null, "n_records": 0, "status": "error", "notes": "Expecting value: line 1 column 1 (char 0)"}, {"ts": "2026-07-18T13:31:48.840655+00:00", "source": "The Metropolitan Museum of Art (Open Access)", "action": "object", "ref": "73158", "http_status": null, "n_records": 0, "status": "error", "notes": "Expecting value: line 1 column 1 (char 0)"}, {"ts": "2026-07-18T13:31:48.839711+00:00", "source": "The Metropolitan Museum of Art (Open Access)", "action": "object", "ref": "38296", "http_status": null, "n_records": 0, "status": "error", "notes": "Expecting value: line 1 column 1 (char 0)"}, {"ts": "2026-07-18T13:31:48.838631+00:00", "source": "The Metropolitan Museum of Art (Open Access)", "action": "object", "ref": "39606", "http_status": null, "n_records": 0, "status": "error", "notes": "Expecting value: line 1 column 1 (char 0)"}, {"ts": "2026-07-18T13:31:48.836248+00:00", "source": "The Metropolitan Museum of Art (Open Access)", "action": "object", "ref": "39097", "http_status": null, "n_records": 0, "status": "error", "notes": "Client error '404 Not Found' for url 'https://collectionapi.metmuseum.org/public/collection/v1/objects/39097'\nFor more information check: https://developer.mozilla.org/en-US/docs/Web/HTTP/Status/404"}, {"ts": "2026-07-18T13:31:47.010003+00:00", "source": "The Metropolitan Museum of Art (Open Access)", "action": "object", "ref": "38315", "http_status": null, "n_records": 0, "status": "error", "notes": "Client error '404 Not Found' for url 'https://collectionapi.metmuseum.org/public/collection/v1/objects/38315'\nFor more information check: https://developer.mozilla.org/en-US/docs/Web/HTTP/Status/404"}, {"ts": "2026-07-18T13:31:45.179477+00:00", "source": "The Metropolitan Museum of Art (Open Access)", "action": "object", "ref": "39184", "http_status": null, "n_records": 0, "status": "error", "notes": "Client error '404 Not Found' for url 'https://collectionapi.metmuseum.org/public/collection/v1/objects/39184'\nFor more information check: https://developer.mozilla.org/en-US/docs/Web/HTTP/Status/404"}, {"ts": "2026-07-18T13:31:43.229434+00:00", "source": "The Metropolitan Museum of Art (Open Access)", "action": "object", "ref": "72341", "http_status": null, "n_records": 0, "status": "error", "notes": "Expecting value: line 1 column 1 (char 0)"}, {"ts": "2026-07-18T13:31:43.228532+00:00", "source": "The Metropolitan Museum of Art (Open Access)", "action": "object", "ref": "72387", "http_status": null, "n_records": 0, "status": "error", "notes": "Expecting value: line 1 column 1 (char 0)"}, {"ts": "2026-07-18T13:31:43.226313+00:00", "source": "The Metropolitan Museum of Art (Open Access)", "action": "object", "ref": "39096", "http_status": null, "n_records": 0, "status": "error", "notes": "Client error '404 Not Found' for url 'https://collectionapi.metmuseum.org/public/collection/v1/objects/39096'\nFor more information check: https://developer.mozilla.org/en-US/docs/Web/HTTP/Status/404"}, {"ts": "2026-07-18T13:31:41.394379+00:00", "source": "The Metropolitan Museum of Art (Open Access)", "action": "object", "ref": "904942", "http_status": null, "n_records": 0, "status": "error", "notes": "Expecting value: line 1 column 1 (char 0)"}, {"ts": "2026-07-18T13:31:41.390739+00:00", "source": "The Metropolitan Museum of Art (Open Access)", "action": "object", "ref": "73651", "http_status": null, "n_records": 0, "status": "error", "notes": "Client error '404 Not Found' for url 'https://collectionapi.metmuseum.org/public/collection/v1/objects/73651'\nFor more information check: https://developer.mozilla.org/en-US/docs/Web/HTTP/Status/404"}, {"ts": "2026-07-18T13:31:39.521388+00:00", "source": "The Metropolitan Museum of Art (Open Access)", "action": "object", "ref": "855995", "http_status": null, "n_records": 0, "status": "error", "notes": "Client error '404 Not Found' for url 'https://collectionapi.metmuseum.org/public/collection/v1/objects/855995'\nFor more information check: https://developer.mozilla.org/en-US/docs/Web/HTTP/Status/404"}, {"ts": "2026-07-18T13:31:37.677807+00:00", "source": "The Metropolitan Museum of Art (Open Access)", "action": "object", "ref": "855382", "http_status": null, "n_records": 0, "status": "error", "notes": "Client error '404 Not Found' for url 'https://collectionapi.metmuseum.org/public/collection/v1/objects/855382'\nFor more information check: https://developer.mozilla.org/en-US/docs/Web/HTTP/Status/404"}, {"ts": "2026-07-18T13:31:35.870005+00:00", "source": "The Metropolitan Museum of Art (Open Access)", "action": "object", "ref": "39097", "http_status": null, "n_records": 0, "status": "error", "notes": "Client error '404 Not Found' for url 'https://collectionapi.metmuseum.org/public/collection/v1/objects/39097'\nFor more information check: https://developer.mozilla.org/en-US/docs/Web/HTTP/Status/404"}, {"ts": "2026-07-18T13:31:34.041949+00:00", "source": "The Metropolitan Museum of Art (Open Access)", "action": "object", "ref": "39096", "http_status": null, "n_records": 0, "status": "error", "notes": "Client error '404 Not Found' for url 'https://collectionapi.metmuseum.org/public/collection/v1/objects/39096'\nFor more information check: https://developer.mozilla.org/en-US/docs/Web/HTTP/Status/404"}, {"ts": "2026-07-18T13:31:31.879800+00:00", "source": "Cleveland Museum of Art (Open Access)", "action": "api_page", "ref": "Indonesia#skip20700", "http_status": null, "n_records": 0, "status": "done", "notes": ""}, {"ts": "2026-07-18T13:31:28.392606+00:00", "source": "Cleveland Museum of Art (Open Access)", "action": "api_page", "ref": "Java#skip20800", "http_status": null, "n_records": 0, "status": "done", "notes": ""}, {"ts": "2026-07-18T13:31:24.830012+00:00", "source": "Cleveland Museum of Art (Open Access)", "action": "api_page", "ref": "Champa#skip20800", "http_status": null, "n_records": 0, "status": "done", "notes": ""}, {"ts": "2026-07-18T13:31:21.345169+00:00", "source": "Cleveland Museum of Art (Open Access)", "action": "api_page", "ref": "Vietnam#skip20800", "http_status": null, "n_records": 0, "status": "done", "notes": ""}, {"ts": "2026-07-18T13:31:17.816854+00:00", "source": "Cleveland Museum of Art (Open Access)", "action": "api_page", "ref": "Burmese#skip20900", "http_status": null, "n_records": 0, "status": "done", "notes": ""}, {"ts": "2026-07-18T13:31:14.294491+00:00", "source": "Cleveland Museum of Art (Open Access)", "action": "api_page", "ref": "Burma#skip21000", "http_status": null, "n_records": 0, "status": "done", "notes": ""}, {"ts": "2026-07-18T13:31:10.775379+00:00", "source": "Cleveland Museum of Art (Open Access)", "action": "api_page", "ref": "Cambodia#skip21100", "http_status": null, "n_records": 0, "status": "done", "notes": ""}, {"ts": "2026-07-18T13:31:07.177024+00:00", "source": "Cleveland Museum of Art (Open Access)", "action": "api_page", "ref": "Khmer#skip21300", "http_status": null, "n_records": 0, "status": "done", "notes": ""}, {"ts": "2026-07-18T13:31:03.688759+00:00", "source": "Cleveland Museum of Art (Open Access)", "action": "api_page", "ref": "Lao#skip21300", "http_status": null, "n_records": 0, "status": "done", "notes": ""}, {"ts": "2026-07-18T13:31:00.218106+00:00", "source": "Cleveland Museum of Art (Open Access)", "action": "api_page", "ref": "Lanna#skip21300", "http_status": null, "n_records": 0, "status": "done", "notes": ""}, {"ts": "2026-07-18T13:30:56.672752+00:00", "source": "Cleveland Museum of Art (Open Access)", "action": "api_page", "ref": "Thai#skip21300", "http_status": null, "n_records": 0, "status": "done", "notes": ""}]}